LICENSE
ways_py/__init__.py
ways_py/ways.py
ways_py-0.1.2.dist-info/LICENSE
ways_py-0.1.2.dist-info/WHEEL
ways_py-0.1.2.dist-info/METADATA
ways_py-0.1.2.dist-info/RECORD
