Metadata-Version: 2.1
Name: ways-py
Version: 0.1.2
Summary: WAYS package for Python developed at University of Warwick and The Alan Turing Institute.
Home-page: https://github.com/WarwickCIM/ways-py
License: MIT
Author: Ed Chalstrey
Author-email: echalstrey@turing.ac.uk
Requires-Python: ==3.9.9
Classifier: License :: OSI Approved :: GNU General Public License v3 (GPLv3)
Classifier: License :: OSI Approved :: MIT License
Classifier: Natural Language :: English
Classifier: Programming Language :: Python :: 3
Classifier: Programming Language :: Python :: 3.9
Requires-Dist: Shapely (>=1.8.0,<2.0.0)
Requires-Dist: altair (>=4.1.0,<5.0.0)
Requires-Dist: altair-saver (>=0.5.0,<0.6.0)
Requires-Dist: certifi (>=2021.10.8,<2022.0.0)
Requires-Dist: importlib-metadata (>=4.8.1,<5.0.0)
Requires-Dist: ipykernel (>=6.4.1,<7.0.0)
Requires-Dist: ipython (>=7.29.0,<8.0.0)
Requires-Dist: ipywidgets (>=7.6.5,<8.0.0)
Requires-Dist: jsonschema (==3.2.0)
Requires-Dist: jupyter (>=1.0.0,<2.0.0)
Requires-Dist: nbmake (>=0.8,<0.9)
Requires-Dist: pdocs (>=1.1.1,<2.0.0)
Requires-Dist: pytest (>=6.2.5,<7.0.0)
Requires-Dist: selenium (>=4.0.0,<5.0.0)
Requires-Dist: vega-datasets (>=0.9.0,<0.10.0)
Project-URL: Documentation, https://warwickcim.github.io/ways-py/
